LICENSE
README.md
setup.cfg
setup.py
r2server/__init__.py
r2server/api.py
r2server/observation.py
r2server/protocol.py
r2server/tle.py
r2server.egg-info/PKG-INFO
r2server.egg-info/SOURCES.txt
r2server.egg-info/dependency_links.txt
r2server.egg-info/requires.txt
r2server.egg-info/top_level.txt
r2server/tools/__init__.py
r2server/tools/common.py