Metadata-Version: 2.1
Name: r2server
Version: 0.0.5
Summary: python SDK for R2SERVER
Home-page: https://github.com/Lukas0025/r2server-python-sdk
Author: Lukáš Plevač
Author-email: lukasplevac@gmail.com
License: UNKNOWN
Platform: UNKNOWN
Classifier: Programming Language :: Python :: 3
Classifier: License :: OSI Approved :: Apache Software License
Classifier: Operating System :: OS Independent
Requires-Python: >=3.0
License-File: LICENSE
